bedframe/_services.py
bedframe/_exc.py
bedframe/_collections.py
bedframe/_methods.py
bedframe/_cors.py
bedframe/_debug.py
bedframe/_requests.py
bedframe/_metadata.py
bedframe/__init__.py
bedframe/http/_services.py
bedframe/http/_exc.py
bedframe/http/__init__.py
bedframe/tornado/_services.py
bedframe/tornado/_handlers.py
bedframe/tornado/_common.py
bedframe/tornado/__init__.py
bedframe/tests/__init__.py
bedframe/webtypes/_core.py
bedframe/webtypes/_misc.py
bedframe/webtypes/_util_json.py
bedframe/webtypes/__init__.py
bedframe/webtypes/_bedframe/_metadata.py
bedframe/webtypes/_bedframe/__init__.py
bedframe/webtypes/_python/_builtin.py
bedframe/webtypes/_python/_datetime.py
bedframe/webtypes/_python/__init__.py
bedframe/_responses/_return.py
bedframe/_responses/_authinfo.py
bedframe/_responses/_exc.py
bedframe/_responses/_redirect.py
bedframe/_responses/_core.py
bedframe/_responses/__init__.py
bedframe/auth/_algorithms.py
bedframe/auth/_exc.py
bedframe/auth/_provisions.py
bedframe/auth/_connectors.py
bedframe/auth/_handlers.py
bedframe/auth/_spaces.py
bedframe/auth/_tokens.py
bedframe/auth/_info.py
bedframe/auth/_authenticators.py
bedframe/auth/__init__.py
bedframe/auth/plain/_algorithms.py
bedframe/auth/plain/__init__.py
bedframe/auth/http/__init__.py
bedframe/auth/http/_basic/_connectors.py
bedframe/auth/http/_basic/__init__.py
bedframe/auth/http/_std/_connectors.py
bedframe/auth/http/_std/__init__.py
bedframe/auth/http/_digest/_connectors.py
bedframe/auth/http/_digest/__init__.py
bedframe/auth/http/_session/_connectors.py
bedframe/auth/http/_session/_managers.py
bedframe/auth/http/_session/__init__.py
bedframe/auth/digest/_algorithms.py
bedframe/auth/digest/__init__.py
bedframe/auth/tornado/__init__.py
bedframe/auth/tornado/_basic/_connectors.py
bedframe/auth/tornado/_basic/__init__.py
bedframe/auth/tornado/_digest/_connectors.py
bedframe/auth/tornado/_digest/__init__.py
Bedframe-0.13.5.dist-info/top_level.txt
Bedframe-0.13.5.dist-info/RECORD
Bedframe-0.13.5.dist-info/pydist.json
Bedframe-0.13.5.dist-info/WHEEL
Bedframe-0.13.5.dist-info/namespace_packages.txt
Bedframe-0.13.5.dist-info/METADATA
Bedframe-0.13.5.dist-info/entry_points.txt
Bedframe-0.13.5.dist-info/DESCRIPTION.rst
