Metadata-Version: 2.0
Name: Bedframe
Version: 0.13.5
Summary: A resource-oriented web services framework
Home-page: UNKNOWN
Author: Ivan D Vasin
Author-email: nisavid@gmail.com
License: GNU LESSER GENERAL PUBLIC LICENSE
Requires-Dist: psutil
Requires-Dist: raven
Requires-Dist: pytz
Requires-Dist: requests (>1)
Requires-Dist: spruce-collections
Requires-Dist: spruce-datetime
Requires-Dist: spruce-lang
Requires-Dist: spruce-logging
Requires-Dist: spruce-pprint
Requires-Dist: spruce-http-common
Requires-Dist: spruce-settings
Requires-Dist: spruce-validation
Requires-Dist: ujson-bedframe
Provides-Extra: tornado
Requires-Dist: tornado-bedframe (>3); extra == 'tornado'
Provides-Extra: test_ldap
Requires-Dist: spruce-ldap[openldap]; extra == 'test_ldap'
Provides-Extra: memcached
Requires-Dist: python-memcached; extra == 'memcached'
Provides-Extra: tornado_wsgi
Requires-Dist: gevent; extra == 'tornado_wsgi'
Requires-Dist: tornado-bedframe (>3); extra == 'tornado_wsgi'
Provides-Extra: ldap
Requires-Dist: python-ldap; extra == 'ldap'
